das_import/__init__.py
das_import/cli.py
das_import/client.py
das_import/exceptions.py
das_import/types.py
das_import-0.1.2.dist-info/LICENSE
das_import-0.1.2.dist-info/METADATA
das_import-0.1.2.dist-info/WHEEL
das_import-0.1.2.dist-info/entry_points.txt
das_import-0.1.2.dist-info/top_level.txt
das_import-0.1.2.dist-info/RECORD
