Metadata-Version: 2.1
Name: das-import
Version: 0.1.2
Summary: Decks Against Society card importer
Home-page: https://github.com/chaosk/das-import
Author: Krzysztof Socha
Author-email: github+das-import@ksocha.com
License: UNKNOWN
Platform: UNKNOWN
Classifier: License :: OSI Approved :: MIT License
Requires-Dist: requests
Requires-Dist: tqdm
